uf2utils/__init__.py
uf2utils/block.py
uf2utils/constants.py
uf2utils/family.py
uf2utils/file.py
uf2utils/header.py
uf2utils/examples/__init__.py
uf2utils/examples/custom_pico.py
uf2utils/examples/extract_binary.py
uf2utils/examples/pico_fs_update.py
uf2utils/examples/uf2_from_scratch.py
uf2utils/examples/uf2_info.py
uf2utils-0.9.6.dist-info/licenses/LICENSE
uf2utils-0.9.6.dist-info/METADATA
uf2utils-0.9.6.dist-info/WHEEL
uf2utils-0.9.6.dist-info/entry_points.txt
uf2utils-0.9.6.dist-info/top_level.txt
uf2utils-0.9.6.dist-info/RECORD
