Metadata-Version: 2.4
Name: uf2utils
Version: 0.9.6
Summary: A flexible and cleanish framework for dealing with UF2 files
Author: Pat Deegan
Project-URL: Homepage, https://github.com/psychogenic/uf2utils
Project-URL: Issues, https://github.com/psychogenic/uf2utils/issues
Classifier: Programming Language :: Python :: 3
Classifier: License :: OSI Approved :: GNU Lesser General Public License v2 or later (LGPLv2+)
Classifier: Operating System :: OS Independent
Requires-Python: >=3.8
License-File: LICENSE
Requires-Dist: littlefs-python>=0.10.0
Dynamic: license-file
